LICENSE
MANIFEST.in
README.rst
setup.py
django_inspect/__init__.py
django_inspect/inspecting.py
django_inspect.egg-info/PKG-INFO
django_inspect.egg-info/SOURCES.txt
django_inspect.egg-info/dependency_links.txt
django_inspect.egg-info/requires.txt
django_inspect.egg-info/top_level.txt
tests/__init__.py
tests/test_inspect.py
tests/test_app/__init__.py
tests/test_app/models.py