Metadata-Version: 1.1
Name: django-inspect
Version: 0.4.1
Summary: Provides inspection conveniences for django models
Home-page: https://github.com/tpisani/django-inspect
Author: Thiago Pisani
Author-email: pisani.thiago@gmail.com
License: BSD
Platform: UNKNOWN
Classifier: Environment :: Web Environment
Classifier: Framework :: Django
Classifier: Intended Audience :: Developers
Classifier: Operating System :: OS Independent
Classifier: Programming Language :: Python :: 2.7
